finmetry/__init__.py
finmetry/constants.py
finmetry/executioners.py
finmetry/utils.py
finmetry/backtest_handler/__init__.py
finmetry/backtest_handler/base.py
finmetry/clients/__init__.py
finmetry/clients/client_5paisa.py
finmetry/portfolio_handler/__init__.py
finmetry/portfolio_handler/base.py
finmetry/stocks_handler/__init__.py
finmetry/stocks_handler/stock.py
finmetry/stocks_handler/stockdict.py
finmetry/strategy_handler/__init__.py
finmetry/strategy_handler/base.py
finmetry-2.0.6.dist-info/METADATA
finmetry-2.0.6.dist-info/WHEEL
finmetry-2.0.6.dist-info/top_level.txt
finmetry-2.0.6.dist-info/RECORD
