Metadata-Version: 2.4
Name: finmetry
Version: 2.0.6
Summary: Persnal project for stock market data analysis
Author-email: Darshan Rathod <darshan.rathod1994@gmail.com>
Maintainer-email: Darshan Rathod <darshan.rathod1994@gmail.com>
License: MIT
Project-URL: Homepage, https://dev-ddr.github.io/finmetry/
Project-URL: Repository, https://github.com/dev-ddr/finmetry
Project-URL: Issues, https://github.com/dev-ddr/finmetry/issues
Keywords: finance,stock-market,quant,research,personal
Classifier: Development Status :: 4 - Beta
Classifier: Programming Language :: Python :: 3.12
Classifier: Operating System :: OS Independent
Requires-Python: >=3.12
Requires-Dist: numpy==2.3.5
Requires-Dist: pandas==2.3.3
Requires-Dist: pyyaml==6.0.3
Requires-Dist: duckdb==1.4.2
Requires-Dist: pyarrow==22.0.0
Requires-Dist: py5paisa==0.7.21.2
Requires-Dist: pydantic
Provides-Extra: dev
Requires-Dist: pytest; extra == "dev"
Requires-Dist: ruff; extra == "dev"
Requires-Dist: jupyter; extra == "dev"
Requires-Dist: notebook; extra == "dev"
Requires-Dist: sphinx; extra == "dev"
Requires-Dist: mkdocs; extra == "dev"
Requires-Dist: mkdocs-material; extra == "dev"
Requires-Dist: mkdocstrings[python]; extra == "dev"
Requires-Dist: nbconvert; extra == "dev"
Requires-Dist: matplotlib; extra == "dev"
Requires-Dist: plotly; extra == "dev"
